{
    "Feature": "Feature title",
    "Scenarios": [
        {
            "Scenario": "Scenario 1 title",
            "Steps": [
                {"Given": "Initial condition"},
                {"When": "An action"},
                {"Then": "An expected outcome"}
            ]
        },
        {
            "Scenario": "Scenario 2 title",
            "Steps": [
                {"Given": "Another initial condition"},
                {"And": "Additional condition"},
                {"When": "Another action"},
                {"Then": "Another expected outcome"},
                {"And": "Further outcome"}
            ]
        }
    ]
}
